zs_server/__init__.py
zs_server/server.py
zs_server-0.1.0.12.dist-info/LICENSE
zs_server-0.1.0.12.dist-info/METADATA
zs_server-0.1.0.12.dist-info/WHEEL
zs_server-0.1.0.12.dist-info/entry_points.txt
zs_server-0.1.0.12.dist-info/top_level.txt
zs_server-0.1.0.12.dist-info/RECORD
